obe/__init__.py
obe/app.py
obe/google.py
obe/microsoft.py
obe/osm.py
obe/overture.py
obe-0.0.9.dist-info/METADATA
obe-0.0.9.dist-info/WHEEL
obe-0.0.9.dist-info/entry_points.txt
obe-0.0.9.dist-info/RECORD
