Metadata-Version: 2.4
Name: obe
Version: 0.0.9
Summary: Open Buildings Extractor
License: MIT
Author: kshitijrajsharma
Author-email: skshitizraj@gmail.com
Requires-Python: >=3.10,<4.0
Classifier: License :: OSI Approved :: MIT License
Classifier: Programming Language :: Python :: 3
Classifier: Programming Language :: Python :: 3.10
Classifier: Programming Language :: Python :: 3.11
Classifier: Programming Language :: Python :: 3.12
Classifier: Programming Language :: Python :: 3.13
Classifier: Programming Language :: Python :: 3.14
Requires-Dist: geopandas (>=1.0.1,<2.0.0)
Requires-Dist: mercantile (>=1.2.1,<2.0.0)
Requires-Dist: overturemaps (>=0.17.0,<0.18.0)
Requires-Dist: pandas (>=2.2.3,<3.0.0)
Requires-Dist: requests (>=2.32.3,<3.0.0)
Requires-Dist: s2sphere (>=0.2.5,<0.3.0)
Requires-Dist: shapely (>=2.0.7,<3.0.0)
Requires-Dist: tqdm (>=4.67.1,<5.0.0)
